[
  {"id":"b36bc1ca-f40a-4a90-b090-f4895299264d","timeZone": "America/Chicago","publicName":"Super Poodle Project!","privateName":"Account 1, Project 1","openTime":"2016-08-01T18:00:00.000Z","closeTime":"2016-08-05T23:59:00.000Z","accountId":"957cdbd9-375f-4d88-9995-195588022459","users":{"total":30},"events":{"total":3,"inactive":2,"active":1},"posts":{"total":256,"last24":128,"last48":7},"backRoom":{"total":4,"last24":2,"last48":1}},
  {"id":"5969898b-adc6-4c23-892b-10bda764522a","timeZone": "America/Chicago","publicName":"Super Hello Kitty Project!","privateName":"Account 1, Project 2","openTime":"2016-09-01T18:00:00.000Z","closeTime":"2016-09-05T23:59:00.000Z","accountId":"957cdbd9-375f-4d88-9995-195588022459","users":{"total":30},"events":{"total":3,"inactive":2,"active":1},"posts":{"total":222,"last24":128,"last48":64},"backRoom":{"total":44,"last24":2,"last48":1}},
  {"id":"7b7f0b39-cf98-4089-85a1-1d4c0db53ee3","timeZone": "America/Chicago","publicName":"Super Manure Project!","privateName":"Account 1, Project 3","openTime":"2016-08-15T18:00:00.000Z","closeTime":"2016-08-20T23:59:00.000Z","accountId":"957cdbd9-375f-4d88-9995-195588022459","users":{"total":30},"events":{"total":3,"inactive":2,"active":1},"posts":{"total":151,"last24":345,"last48":44},"backRoom":{"total":34,"last24":2,"last48":1}},
  {"id":"1b5bb37f-9073-49fa-a106-77cd3e88b166","timeZone": "America/Chicago","publicName":"Meh Starbucks Project!","privateName":"Account 2, Project 1","openTime":"2016-10-01T18:00:00.000Z","closeTime":"2016-10-05T23:59:00.000Z","accountId":"291fad10-8fc4-4e85-9749-be04adcf4295","users":{"total":30},"events":{"total":3,"inactive":2,"active":1},"posts":{"total":212,"last24":52,"last48":66},"backRoom":{"total":31,"last24":2,"last48":1}},
  {"id":"b36bc1ca-f40a-4a90-b090-f48952990987","timeZone": "America/Chicago","publicName":"Meh Therapy Project!","privateName":"Account 3, Project 1","openTime":"2016-07-30T18:00:00.000Z","closeTime":"2016-08-05T23:59:00.000Z","accountId":"0cbd6831-2799-483f-8376-cf05cf07c375","users":{"total":30},"events":{"total":3,"inactive":2,"active":1},"posts":{"total":43,"last24":128,"last48":32},"backRoom":{"total":16,"last24":2,"last48":1}},
  {"id":"5969898b-adc6-4c23-892b-10bda7640987","timeZone": "America/Chicago","publicName":"A Song of Ice and Fire Project!","privateName":"Account 3, Project 2","openTime":"2016-12-25T18:00:00.000Z","closeTime":"2016-12-31T23:59:00.000Z","accountId":"0cbd6831-2799-483f-8376-cf05cf07c375","users":{"total":30},"events":{"total":3,"inactive":2,"active":1},"posts":{"total":54,"last24":44,"last48":64},"backRoom":{"total":33,"last24":2,"last48":1}},
  {"id":"7b7f0b39-cf98-4089-85a1-1d4c0db50987","timeZone": "America/Chicago","publicName":"Game of Drones Project!","privateName":"Account 4, Project 1","openTime":"2016-07-15T18:00:00.000Z","closeTime":"2016-07-20T23:59:00.000Z","accountId":"26632b75-0dbd-4ff4-a422-422f26586566","users":{"total":30},"events":{"total":3,"inactive":2,"active":1},"posts":{"total":256,"last24":128,"last48":64},"backRoom":{"total":71,"last24":3,"last48":1}},
  {"id":"1b5bb37f-9073-49fa-a106-77cd3e880987","timeZone": "America/Chicago","publicName":"Say no More Project!","privateName":"Account 4, Project 2","openTime":"2016-07-31T18:00:00.000Z","closeTime":"2016-08-05T23:59:00.000Z","accountId":"26632b75-0dbd-4ff4-a422-422f26586566","users":{"total":30},"events":{"total":3,"inactive":2,"active":1},"posts":{"total":256,"last24":128,"last48":64},"backRoom":{"total":5,"last24":11,"last48":1}}
]
